discrd_logger/__init__.py
discrd_logger/logger.py
discord_logger_handler-0.1.2.dist-info/LICENSE
discord_logger_handler-0.1.2.dist-info/METADATA
discord_logger_handler-0.1.2.dist-info/WHEEL
discord_logger_handler-0.1.2.dist-info/top_level.txt
discord_logger_handler-0.1.2.dist-info/RECORD
