Metadata-Version: 2.2
Name: discord-logger-handler
Version: 0.1.2
Summary: A logging handler that sends log messages to Discord via webhooks.
Home-page: https://github.com/Tharak01/Discord-Logger-Handler
Author: Tharakeshavan Parthasarathy
Author-email: ptharak01@gmail.com
Classifier: Programming Language :: Python :: 3
Classifier: Operating System :: OS Independent
Requires-Python: >=3.6
License-File: LICENSE
Requires-Dist: requests>=2.20.0
Dynamic: author
Dynamic: author-email
Dynamic: classifier
Dynamic: description
Dynamic: description-content-type
Dynamic: home-page
Dynamic: requires-dist
Dynamic: requires-python
Dynamic: summary
